{
  "Ads": [
    {
      "select_main_ads": "ADMOB",
      "select_backup_ads":"APPLOVIN-D",
      "main_ads_banner": "ca-app-pub-3940256099942544/6300978111",
      "main_ads_intertitial":"ca-app-pub-3940256099942544/1033173712",
      "main_ads_rewards":"",
      "backup_ads_banner":"db4d5e8718b97d78",
      "backup_ads_intertitial":"518cd97722c60b52",
      "backup_ads_rewards":"",
      "open_ads_admob":"",
      "open_ads_alien":"",
      "open_ads_max":"1",
      "interval_intertitial": 5,
      "initialize_sdk":"107355779",
      "initialize_sdk_backup_ads":"",
      "high_paying_keyword_1": "",
      "high_paying_keyword_2": "",
      "high_paying_keyword_3": "",
      "high_paying_keyword_4": "",
      "high_paying_keyword_5": "",
      "status_app": "0",
      "link_redirect": "https://",
      "on_off_category":""
    }
  ],
  "More":
  [
    {
      "id":1,
      "title":"Ludo King",
      "image":"https://lh3.googleusercontent.com/GIa9Ek1a4hyqqulStVT1RC7Mus0K5nOcCaeDpt9sJEekq6lnrSIK7LDrpH0OHlFgwog=s180-rw",
      "link":"https://play.google.com/store/apps/details?id=com.ludo.king"
    },
    {
      "id":2,
      "title":"Homescapes",
      "image":"https://lh3.googleusercontent.com/-mPOu6rWotI9ZLDVnvE3ZqKdTgEfaQaqD5SArpkYwlNJM0fOhJLRfJPpPWACHLezwIQ=s180-rw",
      "link":"https://play.google.com/store/apps/details?id=com.playrix.homescapes"
    },
    {
      "id":3,
      "title":"Minecraft",
      "image":"https://lh3.googleusercontent.com/VSwHQjcAttxsLE47RuS4PqpC4LT7lCoSjE7Hx5AW_yCxtDvcnsHHvm5CTuL5BPN-uRTP=s180-rw",
      "link":"https://play.google.com/store/apps/details?id=com.mojang.minecraftpe"
    }
  ],

  "Categories": [
	{"id":1,"name_category":"Album 1","image": "https://apps.indolokal.com/lightgeneration/file/icons512.png"},
	{"id":2,"name_category":"Album 2","image": "https://apps.indolokal.com/lightgeneration/file/icons512.png"},
	{"id":3,"name_category":"Album 3","image": "https://apps.indolokal.com/lightgeneration/file/icons512.png"},
	{"id":3,"name_category":"Ian Somerhalder & Paul Wesley","image": "https://apps.indolokal.com/lightgeneration/file/icons512.png"},
	{"id":3,"name_category":"Nina Dobrev 1","image": "https://apps.indolokal.com/lightgeneration/file/icons512.png"},
	{"id":3,"name_category":"Nina Dobrev 2","image": "https://apps.indolokal.com/lightgeneration/file/icons512.png"}
  ],

  "Data":
  [
 	{"id":1,"name_category":"Album 1","title":"Wallpapers Album 1","image":"https://images2.imgbox.com/3b/0e/lBHrIZgU_o.jpg"},
	{"id":2,"name_category":"Album 1","title":"Wallpapers Album 1","image":"https://images2.imgbox.com/7f/0d/baIk31P4_o.jpg"},
	{"id":3,"name_category":"Album 1","title":"Wallpapers Album 1","image":"https://images2.imgbox.com/a4/bc/E6UlXUTc_o.jpg"},
	{"id":4,"name_category":"Album 1","title":"Wallpapers Album 1","image":"https://images2.imgbox.com/e0/e3/2gNVOAaz_o.jpg"},
	{"id":5,"name_category":"Album 1","title":"Wallpapers Album 1","image":"https://images2.imgbox.com/66/e6/1wGBP7we_o.jpg"},
	{"id":6,"name_category":"Album 1","title":"Wallpapers Album 1","image":"https://images2.imgbox.com/f3/18/iulYFH76_o.jpg"},
	{"id":7,"name_category":"Album 1","title":"Wallpapers Album 1","image":"https://images2.imgbox.com/cb/25/h6iW0p9k_o.jpg"},
	{"id":8,"name_category":"Album 1","title":"Wallpapers Album 1","image":"https://images2.imgbox.com/88/4d/Z5LGy4Mt_o.png"},
	{"id":9,"name_category":"Album 1","title":"Wallpapers Album 1","image":"https://images2.imgbox.com/ae/ed/ktjRnHI0_o.png"},
	{"id":10,"name_category":"Album 1","title":"Wallpapers Album 1","image":"https://images2.imgbox.com/1f/db/E3YKSCrJ_o.png"},
	{"id":11,"name_category":"Album 1","title":"Wallpapers Album 1","image":"https://images2.imgbox.com/d8/2e/7sDBwfPs_o.jpg"},
	{"id":12,"name_category":"Album 1","title":"Wallpapers Album 1","image":"https://images2.imgbox.com/a0/87/VwDdKS2w_o.jpg"},
	{"id":13,"name_category":"Album 1","title":"Wallpapers Album 1","image":"https://images2.imgbox.com/83/1c/NlR8x7Fw_o.jpg"},
	{"id":14,"name_category":"Album 1","title":"Wallpapers Album 1","image":"https://images2.imgbox.com/56/93/wswWR2DE_o.jpg"},
	{"id":15,"name_category":"Album 1","title":"Wallpapers Album 1","image":"https://images2.imgbox.com/9d/dc/v78doAWl_o.jpg"},
	{"id":16,"name_category":"Album 1","title":"Wallpapers Album 1","image":"https://images2.imgbox.com/e5/98/KaDKALP8_o.png"},
	{"id":17,"name_category":"Album 1","title":"Wallpapers Album 1","image":"https://images2.imgbox.com/81/f1/kaaRuKgx_o.png"},
	{"id":18,"name_category":"Album 1","title":"Wallpapers Album 1","image":"https://images2.imgbox.com/a4/ff/strApILW_o.png"},
	{"id":19,"name_category":"Album 1","title":"Wallpapers Album 1","image":"https://images2.imgbox.com/2a/b2/g5kosSnb_o.jpg"},
	{"id":20,"name_category":"Album 1","title":"Wallpapers Album 1","image":"https://images2.imgbox.com/5b/18/MnKOSNv0_o.jpg"},
	{"id":21,"name_category":"Album 1","title":"Wallpapers Album 1","image":"https://images2.imgbox.com/0e/e8/lCAxNEa7_o.jpg"},
	{"id":22,"name_category":"Album 1","title":"Wallpapers Album 1","image":"https://images2.imgbox.com/c7/6f/CcP5QN49_o.png"},
	{"id":23,"name_category":"Album 1","title":"Wallpapers Album 1","image":"https://images2.imgbox.com/ab/2e/SarDeJtU_o.png"},
	{"id":24,"name_category":"Album 1","title":"Wallpapers Album 1","image":"https://images2.imgbox.com/e2/1c/lbf8gWHv_o.jpg"},
	{"id":25,"name_category":"Album 1","title":"Wallpapers Album 1","image":"https://images2.imgbox.com/d5/84/Rd1Cv5Yt_o.jpg"},
	{"id":26,"name_category":"Album 1","title":"Wallpapers Album 1","image":"https://images2.imgbox.com/c9/78/lNTAZass_o.jpg"},
	{"id":27,"name_category":"Album 1","title":"Wallpapers Album 1","image":"https://images2.imgbox.com/fa/4a/fZmzoM5K_o.jpg"},
	{"id":28,"name_category":"Album 1","title":"Wallpapers Album 1","image":"https://images2.imgbox.com/c6/be/Mez8UDux_o.jpg"},
	{"id":29,"name_category":"Album 1","title":"Wallpapers Album 1","image":"https://images2.imgbox.com/00/ce/OoDBmC8K_o.jpg"},
	{"id":30,"name_category":"Album 1","title":"Wallpapers Album 1","image":"https://images2.imgbox.com/08/3b/uZQ0ZSVa_o.jpg"},
	{"id":31,"name_category":"Album 1","title":"Wallpapers Album 1","image":"https://images2.imgbox.com/67/fb/xRt2SZJF_o.jpg"},
	{"id":32,"name_category":"Album 1","title":"Wallpapers Album 1","image":"https://images2.imgbox.com/f2/e8/hywsDrI3_o.jpg"},
	{"id":33,"name_category":"Album 1","title":"Wallpapers Album 1","image":"https://images2.imgbox.com/d3/e2/C6HWvv3P_o.png"},
	{"id":34,"name_category":"Album 1","title":"Wallpapers Album 1","image":"https://images2.imgbox.com/c2/8e/s6umuc5o_o.jpg"},
	{"id":35,"name_category":"Album 1","title":"Wallpapers Album 1","image":"https://images2.imgbox.com/c2/13/D9NOmhoS_o.jpg"},
	{"id":36,"name_category":"Album 1","title":"Wallpapers Album 1","image":"https://images2.imgbox.com/6e/35/9CDOQ7Ko_o.jpg"},
	{"id":37,"name_category":"Album 1","title":"Wallpapers Album 1","image":"https://images2.imgbox.com/1a/98/9YFMl7ak_o.jpg"},
	{"id":38,"name_category":"Album 1","title":"Wallpapers Album 1","image":"https://images2.imgbox.com/61/71/VU1SLfri_o.jpg"},
	{"id":39,"name_category":"Album 1","title":"Wallpapers Album 1","image":"https://images2.imgbox.com/26/3c/0tzUX96h_o.jpg"},
	{"id":40,"name_category":"Album 1","title":"Wallpapers Album 1","image":"https://images2.imgbox.com/bc/27/c8fNRSzA_o.jpg"},
	{"id":41,"name_category":"Album 2","title":"Wallpapers Album 2","image":"https://images2.imgbox.com/a4/de/APOFCmzG_o.jpg"},
	{"id":42,"name_category":"Album 2","title":"Wallpapers Album 2","image":"https://images2.imgbox.com/c0/79/TibUM6dz_o.jpg"},
	{"id":43,"name_category":"Album 2","title":"Wallpapers Album 2","image":"https://images2.imgbox.com/dc/ee/qEr1sYEE_o.jpg"},
	{"id":44,"name_category":"Album 2","title":"Wallpapers Album 2","image":"https://images2.imgbox.com/1f/58/tIHKAxO7_o.png"},
	{"id":45,"name_category":"Album 2","title":"Wallpapers Album 2","image":"https://images2.imgbox.com/03/d2/4312htRj_o.png"},
	{"id":46,"name_category":"Album 2","title":"Wallpapers Album 2","image":"https://images2.imgbox.com/6f/c3/y0iBa7PM_o.png"},
	{"id":47,"name_category":"Album 2","title":"Wallpapers Album 2","image":"https://images2.imgbox.com/fa/d6/P5F3Ejww_o.jpg"},
	{"id":48,"name_category":"Album 2","title":"Wallpapers Album 2","image":"https://images2.imgbox.com/b8/2f/1KMZRyO2_o.jpg"},
	{"id":49,"name_category":"Album 2","title":"Wallpapers Album 2","image":"https://images2.imgbox.com/4c/df/yFhfWFlQ_o.jpg"},
	{"id":50,"name_category":"Album 2","title":"Wallpapers Album 2","image":"https://images2.imgbox.com/fe/62/KRqEiFtW_o.jpg"},
	{"id":51,"name_category":"Album 2","title":"Wallpapers Album 2","image":"https://images2.imgbox.com/f1/26/J3dn3EYv_o.jpg"},
	{"id":52,"name_category":"Album 2","title":"Wallpapers Album 2","image":"https://images2.imgbox.com/48/17/9g872woq_o.jpg"},
	{"id":53,"name_category":"Album 2","title":"Wallpapers Album 2","image":"https://images2.imgbox.com/68/ef/IoshlPUa_o.jpg"},
	{"id":54,"name_category":"Album 2","title":"Wallpapers Album 2","image":"https://images2.imgbox.com/bc/ca/ftmSPvwq_o.jpg"},
	{"id":55,"name_category":"Album 2","title":"Wallpapers Album 2","image":"https://images2.imgbox.com/23/ab/BCDjWTtN_o.jpg"},
	{"id":56,"name_category":"Album 2","title":"Wallpapers Album 2","image":"https://images2.imgbox.com/03/2e/F9zzGbFH_o.jpg"},
	{"id":57,"name_category":"Album 2","title":"Wallpapers Album 2","image":"https://images2.imgbox.com/08/cc/AVJLYl59_o.jpg"},
	{"id":58,"name_category":"Album 2","title":"Wallpapers Album 2","image":"https://images2.imgbox.com/7f/dc/COfplSTc_o.jpg"},
	{"id":59,"name_category":"Album 2","title":"Wallpapers Album 2","image":"https://images2.imgbox.com/60/49/Asu9NZRc_o.jpg"},
	{"id":60,"name_category":"Album 2","title":"Wallpapers Album 2","image":"https://images2.imgbox.com/0e/74/9ZFsgcBU_o.jpg"},
	{"id":61,"name_category":"Album 2","title":"Wallpapers Album 2","image":"https://images2.imgbox.com/64/b3/0lrVXmjM_o.jpg"},
	{"id":62,"name_category":"Album 2","title":"Wallpapers Album 2","image":"https://images2.imgbox.com/cb/2b/dcbY7sKN_o.jpg"},
	{"id":63,"name_category":"Album 2","title":"Wallpapers Album 2","image":"https://images2.imgbox.com/19/f6/momcJHQ7_o.jpg"},
	{"id":64,"name_category":"Album 2","title":"Wallpapers Album 2","image":"https://images2.imgbox.com/a8/d6/2s4VzNSn_o.jpg"},
	{"id":65,"name_category":"Album 2","title":"Wallpapers Album 2","image":"https://images2.imgbox.com/7f/1e/rMzdxp8e_o.jpg"},
	{"id":66,"name_category":"Album 2","title":"Wallpapers Album 2","image":"https://images2.imgbox.com/54/ed/Zk1Rb7Sf_o.jpg"},
	{"id":67,"name_category":"Album 2","title":"Wallpapers Album 2","image":"https://images2.imgbox.com/c5/41/kNAbgWmf_o.jpg"},
	{"id":68,"name_category":"Album 2","title":"Wallpapers Album 2","image":"https://images2.imgbox.com/1f/80/JQ60ocpy_o.jpg"},
	{"id":69,"name_category":"Album 2","title":"Wallpapers Album 2","image":"https://images2.imgbox.com/c8/e0/8EucS2rF_o.jpg"},
	{"id":70,"name_category":"Album 2","title":"Wallpapers Album 2","image":"https://images2.imgbox.com/07/41/FaD5UFKl_o.jpg"},
	{"id":71,"name_category":"Album 2","title":"Wallpapers Album 2","image":"https://images2.imgbox.com/77/eb/AMJVXEYw_o.jpg"},
	{"id":72,"name_category":"Album 2","title":"Wallpapers Album 2","image":"https://images2.imgbox.com/34/4a/pR8hjilL_o.jpg"},
	{"id":73,"name_category":"Album 2","title":"Wallpapers Album 2","image":"https://images2.imgbox.com/0f/f3/XC888Lzj_o.jpg"},
	{"id":74,"name_category":"Album 2","title":"Wallpapers Album 2","image":"https://images2.imgbox.com/cd/c7/CDyGx95M_o.jpg"},
	{"id":75,"name_category":"Album 2","title":"Wallpapers Album 2","image":"https://images2.imgbox.com/fe/a1/UYLOSfSO_o.jpg"},
	{"id":76,"name_category":"Album 2","title":"Wallpapers Album 2","image":"https://images2.imgbox.com/00/cc/mt6lJ9s1_o.png"},
	{"id":77,"name_category":"Album 2","title":"Wallpapers Album 2","image":"https://images2.imgbox.com/3b/3c/2sOyiq0X_o.jpg"},
	{"id":78,"name_category":"Album 2","title":"Wallpapers Album 2","image":"https://images2.imgbox.com/25/bc/HfYqps7E_o.png"},
	{"id":79,"name_category":"Album 2","title":"Wallpapers Album 2","image":"https://images2.imgbox.com/72/7b/fifPn9X5_o.jpg"},
	{"id":80,"name_category":"Album 2","title":"Wallpapers Album 2","image":"https://images2.imgbox.com/6b/0c/dbW370HE_o.jpg"},
	{"id":81,"name_category":"Album 2","title":"Wallpapers Album 2","image":"https://images2.imgbox.com/d1/e0/FiYRJl0t_o.jpg"},
	{"id":82,"name_category":"Album 2","title":"Wallpapers Album 2","image":"https://images2.imgbox.com/40/0f/wKp2PU0O_o.jpg"},
	{"id":83,"name_category":"Album 2","title":"Wallpapers Album 2","image":"https://images2.imgbox.com/40/92/yHBUh7Ot_o.jpg"},
	{"id":84,"name_category":"Album 2","title":"Wallpapers Album 2","image":"https://images2.imgbox.com/4f/cc/YURaPXPd_o.jpg"},
	{"id":85,"name_category":"Album 2","title":"Wallpapers Album 2","image":"https://images2.imgbox.com/49/44/Qp6FK1JZ_o.jpg"},
	{"id":86,"name_category":"Album 2","title":"Wallpapers Album 2","image":"https://images2.imgbox.com/cd/15/jYsEPDBN_o.jpg"},
	{"id":87,"name_category":"Album 2","title":"Wallpapers Album 2","image":"https://images2.imgbox.com/8a/89/7NcLQdLl_o.jpg"},
	{"id":88,"name_category":"Album 2","title":"Wallpapers Album 2","image":"https://images2.imgbox.com/ea/24/MdoDDKRh_o.jpg"},
	{"id":89,"name_category":"Album 2","title":"Wallpapers Album 2","image":"https://images2.imgbox.com/29/67/4vMKYttX_o.jpg"},
	{"id":90,"name_category":"Album 2","title":"Wallpapers Album 2","image":"https://images2.imgbox.com/4a/48/cWSjN3kY_o.jpg"},
	{"id":91,"name_category":"Album 2","title":"Wallpapers Album 2","image":"https://images2.imgbox.com/31/7d/1nGekrdN_o.png"},
	{"id":92,"name_category":"Album 2","title":"Wallpapers Album 2","image":"https://images2.imgbox.com/e0/d1/Ixw00PoC_o.jpg"},
	{"id":93,"name_category":"Album 2","title":"Wallpapers Album 2","image":"https://images2.imgbox.com/12/a9/P0ArK4ca_o.jpg"},
	{"id":94,"name_category":"Album 2","title":"Wallpapers Album 2","image":"https://images2.imgbox.com/31/23/RcLcVQsK_o.jpg"},
	{"id":95,"name_category":"Album 2","title":"Wallpapers Album 2","image":"https://images2.imgbox.com/b1/9c/VLwSDTNI_o.jpg"},
	{"id":96,"name_category":"Album 2","title":"Wallpapers Album 2","image":"https://images2.imgbox.com/48/01/NGa6snyc_o.jpg"},
	{"id":97,"name_category":"Album 2","title":"Wallpapers Album 2","image":"https://images2.imgbox.com/47/b9/su47W01b_o.jpg"},
	{"id":98,"name_category":"Album 2","title":"Wallpapers Album 2","image":"https://images2.imgbox.com/6f/e8/GH70WRHF_o.jpg"},
	{"id":99,"name_category":"Album 2","title":"Wallpapers Album 2","image":"https://images2.imgbox.com/cd/86/2kLKbM7A_o.jpg"},
	{"id":100,"name_category":"Album 2","title":"Wallpapers Album 2","image":"https://images2.imgbox.com/bc/28/TYCsVWUB_o.jpg"},
	{"id":101,"name_category":"Album 2","title":"Wallpapers Album 2","image":"https://images2.imgbox.com/5c/5e/UmIbmFia_o.jpg"},
	{"id":102,"name_category":"Album 2","title":"Wallpapers Album 2","image":"https://images2.imgbox.com/6b/86/PoeaCIIk_o.jpg"},
	{"id":103,"name_category":"Album 2","title":"Wallpapers Album 2","image":"https://images2.imgbox.com/26/ad/GeTvTBIK_o.jpg"},
	{"id":104,"name_category":"Album 2","title":"Wallpapers Album 2","image":"https://images2.imgbox.com/4c/b4/Qc2jBZCF_o.jpg"},
	{"id":105,"name_category":"Album 2","title":"Wallpapers Album 2","image":"https://images2.imgbox.com/3d/55/1JPKTD6J_o.jpg"},
	{"id":106,"name_category":"Album 2","title":"Wallpapers Album 2","image":"https://images2.imgbox.com/85/e2/6woGEuXW_o.jpg"},
	{"id":107,"name_category":"Album 2","title":"Wallpapers Album 2","image":"https://images2.imgbox.com/16/c9/E0WMGA3c_o.jpg"},
	{"id":108,"name_category":"Album 2","title":"Wallpapers Album 2","image":"https://images2.imgbox.com/ff/4f/suUwlp1S_o.jpg"},
	{"id":109,"name_category":"Album 2","title":"Wallpapers Album 2","image":"https://images2.imgbox.com/70/f5/cJmTIGBD_o.jpg"},
	{"id":110,"name_category":"Album 2","title":"Wallpapers Album 2","image":"https://images2.imgbox.com/ee/c4/shQFWe3N_o.jpg"},
	{"id":111,"name_category":"Album 2","title":"Wallpapers Album 2","image":"https://images2.imgbox.com/fa/a5/ymArPkt9_o.jpg"},
	{"id":112,"name_category":"Album 2","title":"Wallpapers Album 2","image":"https://images2.imgbox.com/9e/04/NptohARH_o.jpg"},
	{"id":113,"name_category":"Album 2","title":"Wallpapers Album 2","image":"https://images2.imgbox.com/66/ac/Zs1M2vdN_o.jpg"},
	{"id":114,"name_category":"Album 2","title":"Wallpapers Album 2","image":"https://images2.imgbox.com/4f/f6/BLlFcbjj_o.jpg"},
	{"id":115,"name_category":"Album 2","title":"Wallpapers Album 2","image":"https://images2.imgbox.com/f3/15/5ilnRjbf_o.jpg"},
	{"id":116,"name_category":"Album 2","title":"Wallpapers Album 2","image":"https://images2.imgbox.com/c2/74/vYS5HEGk_o.jpg"},
	{"id":117,"name_category":"Album 2","title":"Wallpapers Album 2","image":"https://images2.imgbox.com/83/95/qTZWOv11_o.jpg"},
	{"id":118,"name_category":"Album 2","title":"Wallpapers Album 2","image":"https://images2.imgbox.com/4c/7c/2dSYbAGC_o.jpg"},
	{"id":119,"name_category":"Album 2","title":"Wallpapers Album 2","image":"https://images2.imgbox.com/cd/8a/ncLNSv3y_o.jpg"},
	{"id":120,"name_category":"Album 2","title":"Wallpapers Album 2","image":"https://images2.imgbox.com/6a/7a/eIfzg90k_o.jpg"},
	{"id":121,"name_category":"Album 2","title":"Wallpapers Album 2","image":"https://images2.imgbox.com/cf/89/3BNOD4Lg_o.jpg"},
	{"id":122,"name_category":"Album 2","title":"Wallpapers Album 2","image":"https://images2.imgbox.com/8e/8e/XNBI6ADk_o.jpg"},
	{"id":123,"name_category":"Album 2","title":"Wallpapers Album 2","image":"https://images2.imgbox.com/4a/53/nllu744A_o.jpg"},
	{"id":124,"name_category":"Album 2","title":"Wallpapers Album 2","image":"https://images2.imgbox.com/7d/96/G2oMDoQc_o.jpg"},
	{"id":125,"name_category":"Album 2","title":"Wallpapers Album 2","image":"https://images2.imgbox.com/09/9d/yndo3wcs_o.jpg"},
	{"id":126,"name_category":"Album 2","title":"Wallpapers Album 2","image":"https://images2.imgbox.com/84/3f/auvrP2sQ_o.jpg"},
	{"id":127,"name_category":"Album 2","title":"Wallpapers Album 2","image":"https://images2.imgbox.com/f4/68/jRuK07p3_o.jpg"},
	{"id":128,"name_category":"Album 2","title":"Wallpapers Album 2","image":"https://images2.imgbox.com/8a/b9/V0GNqmFt_o.jpg"},
	{"id":129,"name_category":"Album 2","title":"Wallpapers Album 2","image":"https://images2.imgbox.com/55/41/2CsSkSRT_o.jpg"},
	{"id":130,"name_category":"Album 2","title":"Wallpapers Album 2","image":"https://images2.imgbox.com/17/b5/2LTDeJ54_o.jpg"},
	{"id":131,"name_category":"Album 2","title":"Wallpapers Album 2","image":"https://images2.imgbox.com/0c/c7/G8L5fTyf_o.jpg"},
	{"id":132,"name_category":"Album 2","title":"Wallpapers Album 2","image":"https://images2.imgbox.com/e5/fe/6dC58WM1_o.jpg"},
	{"id":133,"name_category":"Album 2","title":"Wallpapers Album 2","image":"https://images2.imgbox.com/9b/27/IPA2MSd3_o.jpg"},
	{"id":134,"name_category":"Album 2","title":"Wallpapers Album 2","image":"https://images2.imgbox.com/41/27/MpcGeUwv_o.jpg"},
	{"id":135,"name_category":"Album 2","title":"Wallpapers Album 2","image":"https://images2.imgbox.com/48/a7/PMzGE1nz_o.jpg"},
	{"id":136,"name_category":"Album 2","title":"Wallpapers Album 2","image":"https://images2.imgbox.com/7e/ba/OqYTw4ui_o.jpg"},
	{"id":137,"name_category":"Album 2","title":"Wallpapers Album 2","image":"https://images2.imgbox.com/35/24/EcN5Kxfc_o.jpg"},
	{"id":138,"name_category":"Album 2","title":"Wallpapers Album 2","image":"https://images2.imgbox.com/24/23/ctum8FO4_o.jpg"},
	{"id":139,"name_category":"Album 2","title":"Wallpapers Album 2","image":"https://images2.imgbox.com/81/b4/ubDdqSw4_o.jpg"},
	{"id":140,"name_category":"Album 2","title":"Wallpapers Album 2","image":"https://images2.imgbox.com/b5/2c/KlQ9cxQ7_o.jpg"},
	{"id":141,"name_category":"Album 2","title":"Wallpapers Album 2","image":"https://images2.imgbox.com/bd/3f/LkMh6VZ7_o.jpg"},
	{"id":142,"name_category":"Album 2","title":"Wallpapers Album 2","image":"https://images2.imgbox.com/63/cd/pjjTq5rY_o.jpg"},
	{"id":143,"name_category":"Album 2","title":"Wallpapers Album 2","image":"https://images2.imgbox.com/79/96/jFh0z9dG_o.jpg"},
	{"id":144,"name_category":"Album 2","title":"Wallpapers Album 2","image":"https://images2.imgbox.com/b9/3f/P0ATDIri_o.jpg"},
	{"id":145,"name_category":"Album 2","title":"Wallpapers Album 2","image":"https://images2.imgbox.com/60/c2/b27AJzi2_o.jpg"},
	{"id":146,"name_category":"Album 2","title":"Wallpapers Album 2","image":"https://images2.imgbox.com/1a/d1/g3x0eS4L_o.jpg"},
	{"id":147,"name_category":"Album 2","title":"Wallpapers Album 2","image":"https://images2.imgbox.com/6d/22/0FBUz3vY_o.jpg"},
	{"id":148,"name_category":"Album 2","title":"Wallpapers Album 2","image":"https://images2.imgbox.com/e0/23/nKgDfI5I_o.jpg"},
	{"id":149,"name_category":"Album 2","title":"Wallpapers Album 2","image":"https://images2.imgbox.com/4f/25/uEGbgtIX_o.jpg"},
	{"id":150,"name_category":"Album 2","title":"Wallpapers Album 2","image":"https://images2.imgbox.com/59/74/i368cqxo_o.jpg"},
	{"id":151,"name_category":"Album 2","title":"Wallpapers Album 2","image":"https://images2.imgbox.com/8f/eb/eiUc3RaG_o.jpg"},
	{"id":152,"name_category":"Album 2","title":"Wallpapers Album 2","image":"https://images2.imgbox.com/45/22/x7N0CRyD_o.jpg"},
	{"id":153,"name_category":"Album 2","title":"Wallpapers Album 2","image":"https://images2.imgbox.com/1c/57/sGYCbmbJ_o.jpg"},
	{"id":154,"name_category":"Album 2","title":"Wallpapers Album 2","image":"https://images2.imgbox.com/b5/a4/GBbeTfHp_o.jpg"},
	{"id":155,"name_category":"Album 2","title":"Wallpapers Album 2","image":"https://images2.imgbox.com/19/89/CWFr8x7I_o.jpg"},
	{"id":156,"name_category":"Album 2","title":"Wallpapers Album 2","image":"https://images2.imgbox.com/88/95/MhgdsQHA_o.jpg"},
	{"id":157,"name_category":"Album 2","title":"Wallpapers Album 2","image":"https://images2.imgbox.com/1f/03/yplbi82c_o.png"},
	{"id":158,"name_category":"Album 2","title":"Wallpapers Album 2","image":"https://images2.imgbox.com/32/c1/PqNmFwhC_o.jpg"},
	{"id":159,"name_category":"Album 2","title":"Wallpapers Album 2","image":"https://images2.imgbox.com/d8/1c/i8k7EWoc_o.jpg"},
	{"id":160,"name_category":"Album 2","title":"Wallpapers Album 2","image":"https://images2.imgbox.com/36/0d/ExH2q7R3_o.jpg"},
	{"id":161,"name_category":"Album 2","title":"Wallpapers Album 2","image":"https://images2.imgbox.com/91/89/zT0cF4E3_o.jpg"},
	{"id":162,"name_category":"Album 2","title":"Wallpapers Album 2","image":"https://images2.imgbox.com/b4/e7/thxq3DTI_o.jpg"},
	{"id":163,"name_category":"Album 2","title":"Wallpapers Album 2","image":"https://images2.imgbox.com/19/ca/0NkA82WS_o.jpg"},
	{"id":164,"name_category":"Album 2","title":"Wallpapers Album 2","image":"https://images2.imgbox.com/2f/b4/11MP92QF_o.jpg"},
	{"id":165,"name_category":"Album 2","title":"Wallpapers Album 2","image":"https://images2.imgbox.com/2d/6b/vii6bf8B_o.jpg"},
	{"id":166,"name_category":"Album 2","title":"Wallpapers Album 2","image":"https://images2.imgbox.com/9e/b1/7UCpR2uG_o.jpg"},
	{"id":167,"name_category":"Album 2","title":"Wallpapers Album 2","image":"https://images2.imgbox.com/3a/d9/Y8x4hmne_o.jpg"},
	{"id":168,"name_category":"Album 2","title":"Wallpapers Album 2","image":"https://images2.imgbox.com/78/4a/Jc3HTYQ7_o.jpg"},
	{"id":169,"name_category":"Album 2","title":"Wallpapers Album 2","image":"https://images2.imgbox.com/1c/95/JVw4ZDkD_o.jpg"},
	{"id":170,"name_category":"Album 2","title":"Wallpapers Album 2","image":"https://images2.imgbox.com/56/d6/sGBl81Iq_o.jpg"},
	{"id":171,"name_category":"Album 2","title":"Wallpapers Album 2","image":"https://images2.imgbox.com/34/37/medDvXgX_o.jpg"},
	{"id":172,"name_category":"Album 2","title":"Wallpapers Album 2","image":"https://images2.imgbox.com/be/5e/6HRKyDVM_o.jpg"},
	{"id":173,"name_category":"Album 2","title":"Wallpapers Album 2","image":"https://images2.imgbox.com/15/a5/bGViWZuc_o.jpg"},
	{"id":174,"name_category":"Album 2","title":"Wallpapers Album 2","image":"https://images2.imgbox.com/82/22/CiaphjOo_o.jpg"},
	{"id":175,"name_category":"Album 2","title":"Wallpapers Album 2","image":"https://images2.imgbox.com/44/16/womSi5uG_o.jpg"},
	{"id":176,"name_category":"Album 2","title":"Wallpapers Album 2","image":"https://images2.imgbox.com/6e/f2/2np5oCEk_o.jpg"},
	{"id":177,"name_category":"Album 2","title":"Wallpapers Album 2","image":"https://images2.imgbox.com/34/c8/Ua4uTqEr_o.jpg"},
	{"id":178,"name_category":"Album 2","title":"Wallpapers Album 2","image":"https://images2.imgbox.com/62/81/gBxewGyM_o.jpg"},
	{"id":179,"name_category":"Album 2","title":"Wallpapers Album 2","image":"https://images2.imgbox.com/f3/ed/VkxGTk8R_o.jpg"},
	{"id":180,"name_category":"Album 2","title":"Wallpapers Album 2","image":"https://images2.imgbox.com/9e/04/vA07lvbL_o.jpg"},
	{"id":181,"name_category":"Album 3","title":"Wallpapers Album 3","image":"https://images2.imgbox.com/4d/60/nlF6GsiE_o.jpg"},
	{"id":182,"name_category":"Album 3","title":"Wallpapers Album 3","image":"https://images2.imgbox.com/7f/d4/czyt3i5R_o.jpg"},
	{"id":183,"name_category":"Album 3","title":"Wallpapers Album 3","image":"https://images2.imgbox.com/7f/c9/YiefzGGA_o.jpg"},
	{"id":184,"name_category":"Album 3","title":"Wallpapers Album 3","image":"https://images2.imgbox.com/99/f9/5Kts3AtG_o.jpg"},
	{"id":185,"name_category":"Album 3","title":"Wallpapers Album 3","image":"https://images2.imgbox.com/4e/8b/ftcL0Nwx_o.jpg"},
	{"id":186,"name_category":"Album 3","title":"Wallpapers Album 3","image":"https://images2.imgbox.com/d6/94/2ckPSDFh_o.jpg"},
	{"id":187,"name_category":"Album 3","title":"Wallpapers Album 3","image":"https://images2.imgbox.com/41/74/EJs0IVGh_o.jpg"},
	{"id":188,"name_category":"Album 3","title":"Wallpapers Album 3","image":"https://images2.imgbox.com/ac/1f/ICYacnYt_o.jpg"},
	{"id":189,"name_category":"Album 3","title":"Wallpapers Album 3","image":"https://images2.imgbox.com/f6/e7/W1fVAKAP_o.jpg"},
	{"id":190,"name_category":"Album 3","title":"Wallpapers Album 3","image":"https://images2.imgbox.com/3c/4a/KhIGqyFG_o.jpg"},
	{"id":191,"name_category":"Album 3","title":"Wallpapers Album 3","image":"https://images2.imgbox.com/5f/d8/YU0qO4Qr_o.jpg"},
	{"id":192,"name_category":"Album 3","title":"Wallpapers Album 3","image":"https://images2.imgbox.com/48/45/nyTcxGtT_o.jpg"},
	{"id":193,"name_category":"Album 3","title":"Wallpapers Album 3","image":"https://images2.imgbox.com/6d/6f/kcuzrYwP_o.jpg"},
	{"id":194,"name_category":"Album 3","title":"Wallpapers Album 3","image":"https://images2.imgbox.com/00/e7/XiDuurOk_o.jpg"},
	{"id":195,"name_category":"Album 3","title":"Wallpapers Album 3","image":"https://images2.imgbox.com/03/3f/OQlnIPyb_o.jpg"},
	{"id":196,"name_category":"Album 3","title":"Wallpapers Album 3","image":"https://images2.imgbox.com/cc/ea/jxkqPt1F_o.jpg"},
	{"id":197,"name_category":"Album 3","title":"Wallpapers Album 3","image":"https://images2.imgbox.com/81/2c/zpxFJXPw_o.jpg"},
	{"id":198,"name_category":"Album 3","title":"Wallpapers Album 3","image":"https://images2.imgbox.com/38/be/iEPHoIpw_o.jpg"},
	{"id":199,"name_category":"Album 3","title":"Wallpapers Album 3","image":"https://images2.imgbox.com/78/e9/JD9FSuli_o.png"},
	{"id":200,"name_category":"Album 3","title":"Wallpapers Album 3","image":"https://images2.imgbox.com/79/b8/S4uCn4vR_o.jpg"},
	{"id":201,"name_category":"Album 3","title":"Wallpapers Album 3","image":"https://images2.imgbox.com/2f/f9/8qD9WZpD_o.jpg"},
	{"id":202,"name_category":"Album 3","title":"Wallpapers Album 3","image":"https://images2.imgbox.com/e8/e2/XVJnpA1s_o.jpg"},
	{"id":203,"name_category":"Album 3","title":"Wallpapers Album 3","image":"https://images2.imgbox.com/5d/28/tI4TrBBc_o.jpg"},
	{"id":204,"name_category":"Album 3","title":"Wallpapers Album 3","image":"https://images2.imgbox.com/eb/40/EtumAPKG_o.jpg"},
	{"id":205,"name_category":"Album 3","title":"Wallpapers Album 3","image":"https://images2.imgbox.com/47/ff/gNxwk0jO_o.jpg"},
	{"id":206,"name_category":"Album 3","title":"Wallpapers Album 3","image":"https://images2.imgbox.com/e5/e0/wCsN2jTF_o.jpg"},
	{"id":207,"name_category":"Album 3","title":"Wallpapers Album 3","image":"https://images2.imgbox.com/d1/61/3oweuex6_o.jpg"},
	{"id":208,"name_category":"Album 3","title":"Wallpapers Album 3","image":"https://images2.imgbox.com/2e/06/lZyyN6n1_o.jpg"},
	{"id":209,"name_category":"Album 3","title":"Wallpapers Album 3","image":"https://images2.imgbox.com/61/3d/QroVN6VQ_o.jpg"},
	{"id":210,"name_category":"Album 3","title":"Wallpapers Album 3","image":"https://images2.imgbox.com/1e/55/9rm6Uimd_o.jpg"},
	{"id":211,"name_category":"Album 3","title":"Wallpapers Album 3","image":"https://images2.imgbox.com/74/ca/TEs2L8jI_o.jpg"},
	{"id":212,"name_category":"Album 3","title":"Wallpapers Album 3","image":"https://images2.imgbox.com/53/84/IyCsQP5I_o.jpg"},
	{"id":213,"name_category":"Album 3","title":"Wallpapers Album 3","image":"https://images2.imgbox.com/32/24/qirft4sI_o.jpg"},
	{"id":214,"name_category":"Album 3","title":"Wallpapers Album 3","image":"https://images2.imgbox.com/ac/6b/l5LHv0BE_o.jpg"},
	{"id":215,"name_category":"Album 3","title":"Wallpapers Album 3","image":"https://images2.imgbox.com/f3/ae/HX8PV6F9_o.jpg"},
	{"id":216,"name_category":"Album 3","title":"Wallpapers Album 3","image":"https://images2.imgbox.com/ec/6a/zwQk2Buv_o.jpg"},
	{"id":217,"name_category":"Album 3","title":"Wallpapers Album 3","image":"https://images2.imgbox.com/59/f6/o99W82xx_o.jpg"},
	{"id":218,"name_category":"Album 3","title":"Wallpapers Album 3","image":"https://images2.imgbox.com/69/32/36DtrNTW_o.jpg"},
	{"id":219,"name_category":"Album 3","title":"Wallpapers Album 3","image":"https://images2.imgbox.com/62/26/80EuXlST_o.jpg"},
	{"id":220,"name_category":"Album 3","title":"Wallpapers Album 3","image":"https://images2.imgbox.com/5c/a2/U1H7AxSo_o.jpg"},

	{"id":221,"name_category":"Ian Somerhalder & Paul Wesley","title":"Ian Somerhalder & Paul Wesley","image":"https://apps.indolokal.com/lightgeneration/images/VampireDiaries/Ian-Somerhalder_Paul-Wesley/1.jpg"},
	{"id":222,"name_category":"Ian Somerhalder & Paul Wesley","title":"Ian Somerhalder & Paul Wesley","image":"https://apps.indolokal.com/lightgeneration/images/VampireDiaries/Ian-Somerhalder_Paul-Wesley/2.jpg"},
	{"id":223,"name_category":"Ian Somerhalder & Paul Wesley","title":"Ian Somerhalder & Paul Wesley","image":"https://apps.indolokal.com/lightgeneration/images/VampireDiaries/Ian-Somerhalder_Paul-Wesley/3.jpg"},
	{"id":224,"name_category":"Ian Somerhalder & Paul Wesley","title":"Ian Somerhalder & Paul Wesley","image":"https://apps.indolokal.com/lightgeneration/images/VampireDiaries/Ian-Somerhalder_Paul-Wesley/4.jpg"},
	{"id":225,"name_category":"Ian Somerhalder & Paul Wesley","title":"Ian Somerhalder & Paul Wesley","image":"https://apps.indolokal.com/lightgeneration/images/VampireDiaries/Ian-Somerhalder_Paul-Wesley/5.jpg"},
	{"id":226,"name_category":"Ian Somerhalder & Paul Wesley","title":"Ian Somerhalder & Paul Wesley","image":"https://apps.indolokal.com/lightgeneration/images/VampireDiaries/Ian-Somerhalder_Paul-Wesley/6.jpg"},
	{"id":227,"name_category":"Ian Somerhalder & Paul Wesley","title":"Ian Somerhalder & Paul Wesley","image":"https://apps.indolokal.com/lightgeneration/images/VampireDiaries/Ian-Somerhalder_Paul-Wesley/7.jpg"},
	{"id":228,"name_category":"Ian Somerhalder & Paul Wesley","title":"Ian Somerhalder & Paul Wesley","image":"https://apps.indolokal.com/lightgeneration/images/VampireDiaries/Ian-Somerhalder_Paul-Wesley/8.jpg"},
	{"id":229,"name_category":"Ian Somerhalder & Paul Wesley","title":"Ian Somerhalder & Paul Wesley","image":"https://apps.indolokal.com/lightgeneration/images/VampireDiaries/Ian-Somerhalder_Paul-Wesley/9.jpg"},
	{"id":230,"name_category":"Ian Somerhalder & Paul Wesley","title":"Ian Somerhalder & Paul Wesley","image":"https://apps.indolokal.com/lightgeneration/images/VampireDiaries/Ian-Somerhalder_Paul-Wesley/10.jpg"},
	{"id":231,"name_category":"Ian Somerhalder & Paul Wesley","title":"Ian Somerhalder & Paul Wesley","image":"https://apps.indolokal.com/lightgeneration/images/VampireDiaries/Ian-Somerhalder_Paul-Wesley/11.jpg"},
	{"id":232,"name_category":"Ian Somerhalder & Paul Wesley","title":"Ian Somerhalder & Paul Wesley","image":"https://apps.indolokal.com/lightgeneration/images/VampireDiaries/Ian-Somerhalder_Paul-Wesley/12.jpg"},
	{"id":233,"name_category":"Ian Somerhalder & Paul Wesley","title":"Ian Somerhalder & Paul Wesley","image":"https://apps.indolokal.com/lightgeneration/images/VampireDiaries/Ian-Somerhalder_Paul-Wesley/13.jpg"},
	{"id":234,"name_category":"Ian Somerhalder & Paul Wesley","title":"Ian Somerhalder & Paul Wesley","image":"https://apps.indolokal.com/lightgeneration/images/VampireDiaries/Ian-Somerhalder_Paul-Wesley/14.jpg"},
	{"id":235,"name_category":"Ian Somerhalder & Paul Wesley","title":"Ian Somerhalder & Paul Wesley","image":"https://apps.indolokal.com/lightgeneration/images/VampireDiaries/Ian-Somerhalder_Paul-Wesley/15.jpg"},
	{"id":236,"name_category":"Ian Somerhalder & Paul Wesley","title":"Ian Somerhalder & Paul Wesley","image":"https://apps.indolokal.com/lightgeneration/images/VampireDiaries/Ian-Somerhalder_Paul-Wesley/16.jpg"},
	{"id":237,"name_category":"Ian Somerhalder & Paul Wesley","title":"Ian Somerhalder & Paul Wesley","image":"https://apps.indolokal.com/lightgeneration/images/VampireDiaries/Ian-Somerhalder_Paul-Wesley/17.jpg"},
	{"id":238,"name_category":"Ian Somerhalder & Paul Wesley","title":"Ian Somerhalder & Paul Wesley","image":"https://apps.indolokal.com/lightgeneration/images/VampireDiaries/Ian-Somerhalder_Paul-Wesley/18.jpg"},
	{"id":239,"name_category":"Ian Somerhalder & Paul Wesley","title":"Ian Somerhalder & Paul Wesley","image":"https://apps.indolokal.com/lightgeneration/images/VampireDiaries/Ian-Somerhalder_Paul-Wesley/19.jpg"},
	{"id":240,"name_category":"Ian Somerhalder & Paul Wesley","title":"Ian Somerhalder & Paul Wesley","image":"https://apps.indolokal.com/lightgeneration/images/VampireDiaries/Ian-Somerhalder_Paul-Wesley/20.jpg"},
	{"id":241,"name_category":"Ian Somerhalder & Paul Wesley","title":"Ian Somerhalder & Paul Wesley","image":"https://apps.indolokal.com/lightgeneration/images/VampireDiaries/Ian-Somerhalder_Paul-Wesley/21.jpg"},
	{"id":242,"name_category":"Ian Somerhalder & Paul Wesley","title":"Ian Somerhalder & Paul Wesley","image":"https://apps.indolokal.com/lightgeneration/images/VampireDiaries/Ian-Somerhalder_Paul-Wesley/22.jpg"},
	{"id":243,"name_category":"Ian Somerhalder & Paul Wesley","title":"Ian Somerhalder & Paul Wesley","image":"https://apps.indolokal.com/lightgeneration/images/VampireDiaries/Ian-Somerhalder_Paul-Wesley/23.jpg"},
	{"id":244,"name_category":"Ian Somerhalder & Paul Wesley","title":"Ian Somerhalder & Paul Wesley","image":"https://apps.indolokal.com/lightgeneration/images/VampireDiaries/Ian-Somerhalder_Paul-Wesley/24.jpg"},
	{"id":245,"name_category":"Ian Somerhalder & Paul Wesley","title":"Ian Somerhalder & Paul Wesley","image":"https://apps.indolokal.com/lightgeneration/images/VampireDiaries/Ian-Somerhalder_Paul-Wesley/25.jpg"},
	{"id":246,"name_category":"Ian Somerhalder & Paul Wesley","title":"Ian Somerhalder & Paul Wesley","image":"https://apps.indolokal.com/lightgeneration/images/VampireDiaries/Ian-Somerhalder_Paul-Wesley/26.jpg"},
	{"id":247,"name_category":"Ian Somerhalder & Paul Wesley","title":"Ian Somerhalder & Paul Wesley","image":"https://apps.indolokal.com/lightgeneration/images/VampireDiaries/Ian-Somerhalder_Paul-Wesley/27.jpg"},
	{"id":248,"name_category":"Ian Somerhalder & Paul Wesley","title":"Ian Somerhalder & Paul Wesley","image":"https://apps.indolokal.com/lightgeneration/images/VampireDiaries/Ian-Somerhalder_Paul-Wesley/28.jpg"},
	{"id":249,"name_category":"Ian Somerhalder & Paul Wesley","title":"Ian Somerhalder & Paul Wesley","image":"https://apps.indolokal.com/lightgeneration/images/VampireDiaries/Ian-Somerhalder_Paul-Wesley/29.jpg"},
	{"id":250,"name_category":"Ian Somerhalder & Paul Wesley","title":"Ian Somerhalder & Paul Wesley","image":"https://apps.indolokal.com/lightgeneration/images/VampireDiaries/Ian-Somerhalder_Paul-Wesley/30.jpg"},
	{"id":251,"name_category":"Ian Somerhalder & Paul Wesley","title":"Ian Somerhalder & Paul Wesley","image":"https://apps.indolokal.com/lightgeneration/images/VampireDiaries/Ian-Somerhalder_Paul-Wesley/31.jpg"},
	{"id":252,"name_category":"Ian Somerhalder & Paul Wesley","title":"Ian Somerhalder & Paul Wesley","image":"https://apps.indolokal.com/lightgeneration/images/VampireDiaries/Ian-Somerhalder_Paul-Wesley/32.jpg"},
	{"id":253,"name_category":"Ian Somerhalder & Paul Wesley","title":"Ian Somerhalder & Paul Wesley","image":"https://apps.indolokal.com/lightgeneration/images/VampireDiaries/Ian-Somerhalder_Paul-Wesley/33.jpg"},
	{"id":254,"name_category":"Ian Somerhalder & Paul Wesley","title":"Ian Somerhalder & Paul Wesley","image":"https://apps.indolokal.com/lightgeneration/images/VampireDiaries/Ian-Somerhalder_Paul-Wesley/34.jpg"},

	{"id":255,"name_category":"Nina Dobrev 1","title":"Album Nina Dobrev 1","image":"https://apps.indolokal.com/lightgeneration/images/VampireDiaries/Nina-Dobrev_1/35.jpg"},
	{"id":256,"name_category":"Nina Dobrev 1","title":"Album Nina Dobrev 1","image":"https://apps.indolokal.com/lightgeneration/images/VampireDiaries/Nina-Dobrev_1/36.jpg"},
	{"id":257,"name_category":"Nina Dobrev 1","title":"Album Nina Dobrev 1","image":"https://apps.indolokal.com/lightgeneration/images/VampireDiaries/Nina-Dobrev_1/37.jpg"},
	{"id":258,"name_category":"Nina Dobrev 1","title":"Album Nina Dobrev 1","image":"https://apps.indolokal.com/lightgeneration/images/VampireDiaries/Nina-Dobrev_1/38.jpg"},
	{"id":259,"name_category":"Nina Dobrev 1","title":"Album Nina Dobrev 1","image":"https://apps.indolokal.com/lightgeneration/images/VampireDiaries/Nina-Dobrev_1/39.jpg"},
	{"id":260,"name_category":"Nina Dobrev 1","title":"Album Nina Dobrev 1","image":"https://apps.indolokal.com/lightgeneration/images/VampireDiaries/Nina-Dobrev_1/40.jpg"},
	{"id":261,"name_category":"Nina Dobrev 1","title":"Album Nina Dobrev 1","image":"https://apps.indolokal.com/lightgeneration/images/VampireDiaries/Nina-Dobrev_1/41.jpg"},
	{"id":262,"name_category":"Nina Dobrev 1","title":"Album Nina Dobrev 1","image":"https://apps.indolokal.com/lightgeneration/images/VampireDiaries/Nina-Dobrev_1/42.jpg"},
	{"id":263,"name_category":"Nina Dobrev 1","title":"Album Nina Dobrev 1","image":"https://apps.indolokal.com/lightgeneration/images/VampireDiaries/Nina-Dobrev_1/43.jpg"},
	{"id":264,"name_category":"Nina Dobrev 1","title":"Album Nina Dobrev 1","image":"https://apps.indolokal.com/lightgeneration/images/VampireDiaries/Nina-Dobrev_1/44.jpg"},
	{"id":265,"name_category":"Nina Dobrev 1","title":"Album Nina Dobrev 1","image":"https://apps.indolokal.com/lightgeneration/images/VampireDiaries/Nina-Dobrev_1/45.jpg"},
	{"id":266,"name_category":"Nina Dobrev 1","title":"Album Nina Dobrev 1","image":"https://apps.indolokal.com/lightgeneration/images/VampireDiaries/Nina-Dobrev_1/46.jpg"},
	{"id":267,"name_category":"Nina Dobrev 1","title":"Album Nina Dobrev 1","image":"https://apps.indolokal.com/lightgeneration/images/VampireDiaries/Nina-Dobrev_1/47.jpg"},
	{"id":268,"name_category":"Nina Dobrev 1","title":"Album Nina Dobrev 1","image":"https://apps.indolokal.com/lightgeneration/images/VampireDiaries/Nina-Dobrev_1/48.jpg"},
	{"id":269,"name_category":"Nina Dobrev 1","title":"Album Nina Dobrev 1","image":"https://apps.indolokal.com/lightgeneration/images/VampireDiaries/Nina-Dobrev_1/49.jpg"},
	{"id":270,"name_category":"Nina Dobrev 1","title":"Album Nina Dobrev 1","image":"https://apps.indolokal.com/lightgeneration/images/VampireDiaries/Nina-Dobrev_1/50.jpg"},
	{"id":271,"name_category":"Nina Dobrev 1","title":"Album Nina Dobrev 1","image":"https://apps.indolokal.com/lightgeneration/images/VampireDiaries/Nina-Dobrev_1/51.jpg"},
	{"id":272,"name_category":"Nina Dobrev 1","title":"Album Nina Dobrev 1","image":"https://apps.indolokal.com/lightgeneration/images/VampireDiaries/Nina-Dobrev_1/52.jpg"},
	{"id":273,"name_category":"Nina Dobrev 1","title":"Album Nina Dobrev 1","image":"https://apps.indolokal.com/lightgeneration/images/VampireDiaries/Nina-Dobrev_1/53.jpg"},
	{"id":274,"name_category":"Nina Dobrev 1","title":"Album Nina Dobrev 1","image":"https://apps.indolokal.com/lightgeneration/images/VampireDiaries/Nina-Dobrev_1/54.jpg"},
	{"id":275,"name_category":"Nina Dobrev 1","title":"Album Nina Dobrev 1","image":"https://apps.indolokal.com/lightgeneration/images/VampireDiaries/Nina-Dobrev_1/55.jpg"},
	{"id":276,"name_category":"Nina Dobrev 1","title":"Album Nina Dobrev 1","image":"https://apps.indolokal.com/lightgeneration/images/VampireDiaries/Nina-Dobrev_1/56.jpg"},
	{"id":277,"name_category":"Nina Dobrev 1","title":"Album Nina Dobrev 1","image":"https://apps.indolokal.com/lightgeneration/images/VampireDiaries/Nina-Dobrev_1/57.jpg"},
	{"id":278,"name_category":"Nina Dobrev 1","title":"Album Nina Dobrev 1","image":"https://apps.indolokal.com/lightgeneration/images/VampireDiaries/Nina-Dobrev_1/58.jpg"},
	{"id":279,"name_category":"Nina Dobrev 1","title":"Album Nina Dobrev 1","image":"https://apps.indolokal.com/lightgeneration/images/VampireDiaries/Nina-Dobrev_1/59.jpg"},
	{"id":280,"name_category":"Nina Dobrev 1","title":"Album Nina Dobrev 1","image":"https://apps.indolokal.com/lightgeneration/images/VampireDiaries/Nina-Dobrev_1/60.jpg"},
	{"id":281,"name_category":"Nina Dobrev 1","title":"Album Nina Dobrev 1","image":"https://apps.indolokal.com/lightgeneration/images/VampireDiaries/Nina-Dobrev_1/61.jpg"},
	{"id":282,"name_category":"Nina Dobrev 1","title":"Album Nina Dobrev 1","image":"https://apps.indolokal.com/lightgeneration/images/VampireDiaries/Nina-Dobrev_1/62.jpg"},
	{"id":283,"name_category":"Nina Dobrev 1","title":"Album Nina Dobrev 1","image":"https://apps.indolokal.com/lightgeneration/images/VampireDiaries/Nina-Dobrev_1/63.jpg"},
	{"id":284,"name_category":"Nina Dobrev 1","title":"Album Nina Dobrev 1","image":"https://apps.indolokal.com/lightgeneration/images/VampireDiaries/Nina-Dobrev_1/64.jpg"},
	{"id":285,"name_category":"Nina Dobrev 1","title":"Album Nina Dobrev 1","image":"https://apps.indolokal.com/lightgeneration/images/VampireDiaries/Nina-Dobrev_1/65.jpg"},
	{"id":286,"name_category":"Nina Dobrev 1","title":"Album Nina Dobrev 1","image":"https://apps.indolokal.com/lightgeneration/images/VampireDiaries/Nina-Dobrev_1/66.jpg"},
	{"id":287,"name_category":"Nina Dobrev 1","title":"Album Nina Dobrev 1","image":"https://apps.indolokal.com/lightgeneration/images/VampireDiaries/Nina-Dobrev_1/67.jpg"},
	{"id":288,"name_category":"Nina Dobrev 1","title":"Album Nina Dobrev 1","image":"https://apps.indolokal.com/lightgeneration/images/VampireDiaries/Nina-Dobrev_1/68.jpg"},
	{"id":289,"name_category":"Nina Dobrev 1","title":"Album Nina Dobrev 1","image":"https://apps.indolokal.com/lightgeneration/images/VampireDiaries/Nina-Dobrev_1/69.jpg"},
	{"id":290,"name_category":"Nina Dobrev 1","title":"Album Nina Dobrev 1","image":"https://apps.indolokal.com/lightgeneration/images/VampireDiaries/Nina-Dobrev_1/70.jpg"},
	{"id":291,"name_category":"Nina Dobrev 1","title":"Album Nina Dobrev 1","image":"https://apps.indolokal.com/lightgeneration/images/VampireDiaries/Nina-Dobrev_1/71.jpg"},
	{"id":292,"name_category":"Nina Dobrev 1","title":"Album Nina Dobrev 1","image":"https://apps.indolokal.com/lightgeneration/images/VampireDiaries/Nina-Dobrev_1/72.jpg"},
	{"id":293,"name_category":"Nina Dobrev 1","title":"Album Nina Dobrev 1","image":"https://apps.indolokal.com/lightgeneration/images/VampireDiaries/Nina-Dobrev_1/73.jpg"},
	{"id":294,"name_category":"Nina Dobrev 1","title":"Album Nina Dobrev 1","image":"https://apps.indolokal.com/lightgeneration/images/VampireDiaries/Nina-Dobrev_1/74.jpg"},
	{"id":295,"name_category":"Nina Dobrev 1","title":"Album Nina Dobrev 1","image":"https://apps.indolokal.com/lightgeneration/images/VampireDiaries/Nina-Dobrev_1/75.jpg"},
	{"id":296,"name_category":"Nina Dobrev 1","title":"Album Nina Dobrev 1","image":"https://apps.indolokal.com/lightgeneration/images/VampireDiaries/Nina-Dobrev_1/76.jpg"},
	{"id":297,"name_category":"Nina Dobrev 1","title":"Album Nina Dobrev 1","image":"https://apps.indolokal.com/lightgeneration/images/VampireDiaries/Nina-Dobrev_1/77.jpg"},
	{"id":298,"name_category":"Nina Dobrev 1","title":"Album Nina Dobrev 1","image":"https://apps.indolokal.com/lightgeneration/images/VampireDiaries/Nina-Dobrev_1/78.jpg"},
	{"id":299,"name_category":"Nina Dobrev 1","title":"Album Nina Dobrev 1","image":"https://apps.indolokal.com/lightgeneration/images/VampireDiaries/Nina-Dobrev_1/79.jpg"},
	{"id":300,"name_category":"Nina Dobrev 1","title":"Album Nina Dobrev 1","image":"https://apps.indolokal.com/lightgeneration/images/VampireDiaries/Nina-Dobrev_1/80.jpg"},
	{"id":301,"name_category":"Nina Dobrev 1","title":"Album Nina Dobrev 1","image":"https://apps.indolokal.com/lightgeneration/images/VampireDiaries/Nina-Dobrev_1/81.jpg"},
	{"id":302,"name_category":"Nina Dobrev 1","title":"Album Nina Dobrev 1","image":"https://apps.indolokal.com/lightgeneration/images/VampireDiaries/Nina-Dobrev_1/82.jpg"},
	{"id":303,"name_category":"Nina Dobrev 1","title":"Album Nina Dobrev 1","image":"https://apps.indolokal.com/lightgeneration/images/VampireDiaries/Nina-Dobrev_1/83.jpg"},
	{"id":304,"name_category":"Nina Dobrev 1","title":"Album Nina Dobrev 1","image":"https://apps.indolokal.com/lightgeneration/images/VampireDiaries/Nina-Dobrev_1/84.jpg"},
	{"id":305,"name_category":"Nina Dobrev 1","title":"Album Nina Dobrev 1","image":"https://apps.indolokal.com/lightgeneration/images/VampireDiaries/Nina-Dobrev_1/85.jpg"},
	{"id":306,"name_category":"Nina Dobrev 1","title":"Album Nina Dobrev 1","image":"https://apps.indolokal.com/lightgeneration/images/VampireDiaries/Nina-Dobrev_1/86.jpg"},
	{"id":307,"name_category":"Nina Dobrev 1","title":"Album Nina Dobrev 1","image":"https://apps.indolokal.com/lightgeneration/images/VampireDiaries/Nina-Dobrev_1/87.jpg"},
	{"id":308,"name_category":"Nina Dobrev 1","title":"Album Nina Dobrev 1","image":"https://apps.indolokal.com/lightgeneration/images/VampireDiaries/Nina-Dobrev_1/88.jpg"},
	{"id":309,"name_category":"Nina Dobrev 1","title":"Album Nina Dobrev 1","image":"https://apps.indolokal.com/lightgeneration/images/VampireDiaries/Nina-Dobrev_1/89.jpg"},
	{"id":310,"name_category":"Nina Dobrev 1","title":"Album Nina Dobrev 1","image":"https://apps.indolokal.com/lightgeneration/images/VampireDiaries/Nina-Dobrev_1/90.jpg"},
	{"id":311,"name_category":"Nina Dobrev 1","title":"Album Nina Dobrev 1","image":"https://apps.indolokal.com/lightgeneration/images/VampireDiaries/Nina-Dobrev_1/91.jpg"},
	{"id":312,"name_category":"Nina Dobrev 1","title":"Album Nina Dobrev 1","image":"https://apps.indolokal.com/lightgeneration/images/VampireDiaries/Nina-Dobrev_1/92.jpg"},
	{"id":313,"name_category":"Nina Dobrev 1","title":"Album Nina Dobrev 1","image":"https://apps.indolokal.com/lightgeneration/images/VampireDiaries/Nina-Dobrev_1/93.jpg"},
	{"id":314,"name_category":"Nina Dobrev 1","title":"Album Nina Dobrev 1","image":"https://apps.indolokal.com/lightgeneration/images/VampireDiaries/Nina-Dobrev_1/94.jpg"},

	{"id":315,"name_category":"Nina Dobrev 2","title":"Album Nina Dobrev 2","image":"https://apps.indolokal.com/lightgeneration/images/VampireDiaries/Nina-Dobrev_2/95.jpg"},
	{"id":316,"name_category":"Nina Dobrev 2","title":"Album Nina Dobrev 2","image":"https://apps.indolokal.com/lightgeneration/images/VampireDiaries/Nina-Dobrev_2/96.jpg"},
	{"id":317,"name_category":"Nina Dobrev 2","title":"Album Nina Dobrev 2","image":"https://apps.indolokal.com/lightgeneration/images/VampireDiaries/Nina-Dobrev_2/97.jpg"},
	{"id":318,"name_category":"Nina Dobrev 2","title":"Album Nina Dobrev 2","image":"https://apps.indolokal.com/lightgeneration/images/VampireDiaries/Nina-Dobrev_2/98.jpg"},
	{"id":319,"name_category":"Nina Dobrev 2","title":"Album Nina Dobrev 2","image":"https://apps.indolokal.com/lightgeneration/images/VampireDiaries/Nina-Dobrev_2/99.jpg"},
	{"id":320,"name_category":"Nina Dobrev 2","title":"Album Nina Dobrev 2","image":"https://apps.indolokal.com/lightgeneration/images/VampireDiaries/Nina-Dobrev_2/100.jpg"},
	{"id":321,"name_category":"Nina Dobrev 2","title":"Album Nina Dobrev 2","image":"https://apps.indolokal.com/lightgeneration/images/VampireDiaries/Nina-Dobrev_2/101.jpg"},
	{"id":322,"name_category":"Nina Dobrev 2","title":"Album Nina Dobrev 2","image":"https://apps.indolokal.com/lightgeneration/images/VampireDiaries/Nina-Dobrev_2/102.jpg"},
	{"id":323,"name_category":"Nina Dobrev 2","title":"Album Nina Dobrev 2","image":"https://apps.indolokal.com/lightgeneration/images/VampireDiaries/Nina-Dobrev_2/103.jpg"},
	{"id":324,"name_category":"Nina Dobrev 2","title":"Album Nina Dobrev 2","image":"https://apps.indolokal.com/lightgeneration/images/VampireDiaries/Nina-Dobrev_2/104.jpg"},
	{"id":325,"name_category":"Nina Dobrev 2","title":"Album Nina Dobrev 2","image":"https://apps.indolokal.com/lightgeneration/images/VampireDiaries/Nina-Dobrev_2/105.jpg"},
	{"id":326,"name_category":"Nina Dobrev 2","title":"Album Nina Dobrev 2","image":"https://apps.indolokal.com/lightgeneration/images/VampireDiaries/Nina-Dobrev_2/106.jpg"},
	{"id":327,"name_category":"Nina Dobrev 2","title":"Album Nina Dobrev 2","image":"https://apps.indolokal.com/lightgeneration/images/VampireDiaries/Nina-Dobrev_2/107.jpg"},
	{"id":328,"name_category":"Nina Dobrev 2","title":"Album Nina Dobrev 2","image":"https://apps.indolokal.com/lightgeneration/images/VampireDiaries/Nina-Dobrev_2/108.jpg"},
	{"id":329,"name_category":"Nina Dobrev 2","title":"Album Nina Dobrev 2","image":"https://apps.indolokal.com/lightgeneration/images/VampireDiaries/Nina-Dobrev_2/109.jpg"},
	{"id":330,"name_category":"Nina Dobrev 2","title":"Album Nina Dobrev 2","image":"https://apps.indolokal.com/lightgeneration/images/VampireDiaries/Nina-Dobrev_2/110.jpg"},
	{"id":331,"name_category":"Nina Dobrev 2","title":"Album Nina Dobrev 2","image":"https://apps.indolokal.com/lightgeneration/images/VampireDiaries/Nina-Dobrev_2/111.jpg"},
	{"id":332,"name_category":"Nina Dobrev 2","title":"Album Nina Dobrev 2","image":"https://apps.indolokal.com/lightgeneration/images/VampireDiaries/Nina-Dobrev_2/112.jpg"},
	{"id":333,"name_category":"Nina Dobrev 2","title":"Album Nina Dobrev 2","image":"https://apps.indolokal.com/lightgeneration/images/VampireDiaries/Nina-Dobrev_2/113.jpg"},
	{"id":334,"name_category":"Nina Dobrev 2","title":"Album Nina Dobrev 2","image":"https://apps.indolokal.com/lightgeneration/images/VampireDiaries/Nina-Dobrev_2/114.jpg"},
	{"id":335,"name_category":"Nina Dobrev 2","title":"Album Nina Dobrev 2","image":"https://apps.indolokal.com/lightgeneration/images/VampireDiaries/Nina-Dobrev_2/115.jpg"},
	{"id":336,"name_category":"Nina Dobrev 2","title":"Album Nina Dobrev 2","image":"https://apps.indolokal.com/lightgeneration/images/VampireDiaries/Nina-Dobrev_2/116.jpg"},
	{"id":337,"name_category":"Nina Dobrev 2","title":"Album Nina Dobrev 2","image":"https://apps.indolokal.com/lightgeneration/images/VampireDiaries/Nina-Dobrev_2/117.jpg"},
	{"id":338,"name_category":"Nina Dobrev 2","title":"Album Nina Dobrev 2","image":"https://apps.indolokal.com/lightgeneration/images/VampireDiaries/Nina-Dobrev_2/118.jpg"},
	{"id":339,"name_category":"Nina Dobrev 2","title":"Album Nina Dobrev 2","image":"https://apps.indolokal.com/lightgeneration/images/VampireDiaries/Nina-Dobrev_2/119.jpg"},
	{"id":340,"name_category":"Nina Dobrev 2","title":"Album Nina Dobrev 2","image":"https://apps.indolokal.com/lightgeneration/images/VampireDiaries/Nina-Dobrev_2/120.jpg"},
	{"id":341,"name_category":"Nina Dobrev 2","title":"Album Nina Dobrev 2","image":"https://apps.indolokal.com/lightgeneration/images/VampireDiaries/Nina-Dobrev_2/121.jpg"},
	{"id":342,"name_category":"Nina Dobrev 2","title":"Album Nina Dobrev 2","image":"https://apps.indolokal.com/lightgeneration/images/VampireDiaries/Nina-Dobrev_2/122.jpg"},
	{"id":343,"name_category":"Nina Dobrev 2","title":"Album Nina Dobrev 2","image":"https://apps.indolokal.com/lightgeneration/images/VampireDiaries/Nina-Dobrev_2/123.jpg"},
	{"id":344,"name_category":"Nina Dobrev 2","title":"Album Nina Dobrev 2","image":"https://apps.indolokal.com/lightgeneration/images/VampireDiaries/Nina-Dobrev_2/124.jpg"},
	{"id":345,"name_category":"Nina Dobrev 2","title":"Album Nina Dobrev 2","image":"https://apps.indolokal.com/lightgeneration/images/VampireDiaries/Nina-Dobrev_2/125.jpg"},
	{"id":346,"name_category":"Nina Dobrev 2","title":"Album Nina Dobrev 2","image":"https://apps.indolokal.com/lightgeneration/images/VampireDiaries/Nina-Dobrev_2/126.jpg"},
	{"id":347,"name_category":"Nina Dobrev 2","title":"Album Nina Dobrev 2","image":"https://apps.indolokal.com/lightgeneration/images/VampireDiaries/Nina-Dobrev_2/127.jpg"},
	{"id":348,"name_category":"Nina Dobrev 2","title":"Album Nina Dobrev 2","image":"https://apps.indolokal.com/lightgeneration/images/VampireDiaries/Nina-Dobrev_2/128.jpg"},
	{"id":349,"name_category":"Nina Dobrev 2","title":"Album Nina Dobrev 2","image":"https://apps.indolokal.com/lightgeneration/images/VampireDiaries/Nina-Dobrev_2/129.jpg"},
	{"id":350,"name_category":"Nina Dobrev 2","title":"Album Nina Dobrev 2","image":"https://apps.indolokal.com/lightgeneration/images/VampireDiaries/Nina-Dobrev_2/130.jpg"},
	{"id":351,"name_category":"Nina Dobrev 2","title":"Album Nina Dobrev 2","image":"https://apps.indolokal.com/lightgeneration/images/VampireDiaries/Nina-Dobrev_2/131.jpg"},
	{"id":352,"name_category":"Nina Dobrev 2","title":"Album Nina Dobrev 2","image":"https://apps.indolokal.com/lightgeneration/images/VampireDiaries/Nina-Dobrev_2/132.jpg"},
	{"id":353,"name_category":"Nina Dobrev 2","title":"Album Nina Dobrev 2","image":"https://apps.indolokal.com/lightgeneration/images/VampireDiaries/Nina-Dobrev_2/133.jpg"},
	{"id":354,"name_category":"Nina Dobrev 2","title":"Album Nina Dobrev 2","image":"https://apps.indolokal.com/lightgeneration/images/VampireDiaries/Nina-Dobrev_2/134.jpg"},
	{"id":355,"name_category":"Nina Dobrev 2","title":"Album Nina Dobrev 2","image":"https://apps.indolokal.com/lightgeneration/images/VampireDiaries/Nina-Dobrev_2/135.jpg"},
	{"id":356,"name_category":"Nina Dobrev 2","title":"Album Nina Dobrev 2","image":"https://apps.indolokal.com/lightgeneration/images/VampireDiaries/Nina-Dobrev_2/136.jpg"},
	{"id":357,"name_category":"Nina Dobrev 2","title":"Album Nina Dobrev 2","image":"https://apps.indolokal.com/lightgeneration/images/VampireDiaries/Nina-Dobrev_2/137.jpg"},
	{"id":358,"name_category":"Nina Dobrev 2","title":"Album Nina Dobrev 2","image":"https://apps.indolokal.com/lightgeneration/images/VampireDiaries/Nina-Dobrev_2/138.jpg"},
	{"id":359,"name_category":"Nina Dobrev 2","title":"Album Nina Dobrev 2","image":"https://apps.indolokal.com/lightgeneration/images/VampireDiaries/Nina-Dobrev_2/139.jpg"},
	{"id":360,"name_category":"Nina Dobrev 2","title":"Album Nina Dobrev 2","image":"https://apps.indolokal.com/lightgeneration/images/VampireDiaries/Nina-Dobrev_2/140.jpg"},
	{"id":361,"name_category":"Nina Dobrev 2","title":"Album Nina Dobrev 2","image":"https://apps.indolokal.com/lightgeneration/images/VampireDiaries/Nina-Dobrev_2/141.jpg"},
	{"id":362,"name_category":"Nina Dobrev 2","title":"Album Nina Dobrev 2","image":"https://apps.indolokal.com/lightgeneration/images/VampireDiaries/Nina-Dobrev_2/142.jpg"},
	{"id":363,"name_category":"Nina Dobrev 2","title":"Album Nina Dobrev 2","image":"https://apps.indolokal.com/lightgeneration/images/VampireDiaries/Nina-Dobrev_2/143.jpg"},
	{"id":364,"name_category":"Nina Dobrev 2","title":"Album Nina Dobrev 2","image":"https://apps.indolokal.com/lightgeneration/images/VampireDiaries/Nina-Dobrev_2/144.jpg"},
	{"id":365,"name_category":"Nina Dobrev 2","title":"Album Nina Dobrev 2","image":"https://apps.indolokal.com/lightgeneration/images/VampireDiaries/Nina-Dobrev_2/145.jpg"},
	{"id":366,"name_category":"Nina Dobrev 2","title":"Album Nina Dobrev 2","image":"https://apps.indolokal.com/lightgeneration/images/VampireDiaries/Nina-Dobrev_2/146.jpg"},
	{"id":367,"name_category":"Nina Dobrev 2","title":"Album Nina Dobrev 2","image":"https://apps.indolokal.com/lightgeneration/images/VampireDiaries/Nina-Dobrev_2/147.jpg"},
	{"id":368,"name_category":"Nina Dobrev 2","title":"Album Nina Dobrev 2","image":"https://apps.indolokal.com/lightgeneration/images/VampireDiaries/Nina-Dobrev_2/148.jpg"},
	{"id":369,"name_category":"Nina Dobrev 2","title":"Album Nina Dobrev 2","image":"https://apps.indolokal.com/lightgeneration/images/VampireDiaries/Nina-Dobrev_2/149.jpg"},
	{"id":370,"name_category":"Nina Dobrev 2","title":"Album Nina Dobrev 2","image":"https://apps.indolokal.com/lightgeneration/images/VampireDiaries/Nina-Dobrev_2/150.jpg"},
	{"id":371,"name_category":"Nina Dobrev 2","title":"Album Nina Dobrev 2","image":"https://apps.indolokal.com/lightgeneration/images/VampireDiaries/Nina-Dobrev_2/151.jpg"},
	{"id":372,"name_category":"Nina Dobrev 2","title":"Album Nina Dobrev 2","image":"https://apps.indolokal.com/lightgeneration/images/VampireDiaries/Nina-Dobrev_2/152.jpg"}
  ]
}
